Lab05-part2/second-marking/temp3/16217/register_file_module.v



module reg_file(IN, OUT1, OUT2, INADDRESS, OUT1ADDRESS, OUT2ADDRESS, WRITE, CLK, RESET);
	input [7:0] IN;
	input [2:0] INADDRESS, OUT1ADDRESS, OUT2ADDRESS; //input output addresses
	input WRITE, CLK, RESET;				
	                                        		
	output [7:0] OUT1, OUT2;
	
	//reg [7:0] OUT1, OUT2;
	                                                //registers as an array
	reg [7:0] registers [7:0];
	       
	integer i; 
	
	assign	OUT1 = registers[OUT1ADDRESS];				//always set OUT1 to data in OUT1ADDRESS th register 
	assign OUT2 = registers[OUT2ADDRESS];              //always set OUT2 to data in OUT2ADDRESS th register 
	
	always @ (posedge CLK) begin                       //only work with positive edge

		
		if(WRITE == 1'b1) 
			registers[INADDRESS] = IN;              //if write enabled update data in INADDRESS
			
		
	end
	
	

	
	
	always @ (RESET) begin
		if(RESET == 1'b1)  begin                         //reset all the registers 
		    
			for (i = 0; i < 8; i = i+1)
				registers[i] = 8'b0000_0000;
            
			i = 0;
		 end 
	end			
				
			
endmodule

Lab05-part2/second-marking/temp3/16054/reg_file_tb_groundtruth.v
module reg_file_tb_groundtruth;
    
    reg [7:0] WRITEDATA;
    reg [2:0] WRITEREG, READREG1, READREG2;
    reg CLK, RESET, WRITEENABLE; 
    wire [7:0] REGOUT1, REGOUT2;
    
    reg_file myregfile(WRITEDATA, REGOUT1, REGOUT2, WRITEREG, READREG1, READREG2, WRITEENABLE, CLK, RESET);
       
    initial
    begin
        CLK = 1'b1;
        
        // generate files needed to plot the waveform using GTKWave
        $dumpfile("waveDump.vcd");
		$dumpvars(1, reg_file_tb_groundtruth);
        
        // assign values with time to input signals to see output 
        RESET = 1'b0;
        WRITEENABLE = 1'b0;
        
        #1
        RESET = 1'b1;
        READREG1 = 3'd0;
        READREG2 = 3'd4;
        
        #8
        RESET = 1'b0;
        
        #11
        READREG1 = 3'd2;
        WRITEREG = 3'd2;
        WRITEDATA = 8'd95;
        WRITEENABLE = 1'b1;
        
        #10
        WRITEENABLE = 1'b0;
        
        #1
        READREG1 = 3'd2;
        
        #9
        WRITEREG = 3'd1;
        WRITEDATA = 8'd28;
        WRITEENABLE = 1'b1;
        READREG1 = 3'd1;
        
        #10
        WRITEENABLE = 1'b0;
        
        #10
        WRITEREG = 3'd4;
        WRITEDATA = 8'd6;
        WRITEENABLE = 1'b1;
        
        #10
        WRITEDATA = 8'd15;
        WRITEENABLE = 1'b1;
        
        #10
        WRITEENABLE = 1'b0;
        
        #6
        WRITEREG = 3'd1;
        WRITEDATA = 8'd50;
        WRITEENABLE = 1'b1;
        
        #5
        WRITEENABLE = 1'b0;
        
        #10
        $finish;
    end
    
    // clock signal generation
    always
        #5 CLK = ~CLK;
        

endmodule

Lab05-part2/second-marking/temp3/16217/waveDump.vcd
$date
	Sun May 10 13:59:05 2020
$end
$version
	Icarus Verilog
$end
$timescale
	1s
$end
$scope module reg_file_tb_groundtruth $end
$var wire 8 ! REGOUT1 [7:0] $end
$var wire 8 " REGOUT2 [7:0] $end
$var reg 1 # CLK $end
$var reg 3 $ READREG1 [2:0] $end
$var reg 3 % READREG2 [2:0] $end
$var reg 1 & RESET $end
$var reg 8 ' WRITEDATA [7:0] $end
$var reg 1 ( WRITEENABLE $end
$var reg 3 ) WRITEREG [2:0] $end
$upscope $end
$enddefinitions $end
#0
$dumpvars
bx )
0(
bx '
0&
bx %
bx $
1#
bx "
bx !
$end
#1
b0 "
b0 !
b100 %
b0 $
1&
#5
0#
#9
0&
#10
1#
#15
0#
#20
b1011111 !
1#
1(
b1011111 '
b10 )
b10 $
#25
0#
#30
1#
0(
#35
0#
#40
1#
b1 $
b11100 !
1(
b11100 '
b1 )
#45
0#
#50
1#
0(
#55
0#
#60
b110 "
1#
1(
b110 '
b100 )
#65
0#
#70
b1111 "
1#
b1111 '
#75
0#
#80
1#
0(
#85
0#
#86
1(
b110010 '
b1 )
#90
b110010 !
1#
#91
0(
