Lab05-part2/corrections/TOEDIT/16070/regfile_tb.v
/*
E/16/070
DE SILVA N.S.C.K.S.
LAB05 PART2_TESTBENCH
*/

// testbench for register file
module reg_file_tb;
    
    reg [7:0] WRITEDATA;
    reg [2:0] WRITEREG, READREG1, READREG2;
    reg CLK, RESET, WRITEENABLE; 
    wire [7:0] REGOUT1, REGOUT2;
    
    reg_file myregfile(WRITEDATA, REGOUT1, REGOUT2, WRITEREG, READREG1, READREG2, WRITEENABLE, CLK, RESET);
       
    initial
    begin
        CLK = 1'b1;
        
        // generate files needed to plot the waveform using GTKWave
        $dumpfile("reg_file_wavedata.vcd");
		$dumpvars(0, reg_file_tb);
        
        // assign values with time to input signals to see output 
        RESET = 1'b0;
        WRITEENABLE = 1'b0;
        
        #1
        RESET = 1'b1;
        READREG1 = 3'd2;
        READREG2 = 3'd6;
        
        #8
        RESET = 1'b0;
        
        #5
        WRITEREG = 3'd7;
        WRITEDATA = 8'd17;
        WRITEENABLE = 1'b1;
        
        #10
        WRITEENABLE = 1'b0;
        
        #2
        READREG1 = 3'd7;
        
        #9
        WRITEREG = 3'd2;
        WRITEDATA = 8'd37;
        WRITEENABLE = 1'b1;
        READREG1 = 3'd2;
	RESET = 1'b1 ;

	#10
	RESET = 1'b0 ;
        
        #6
        WRITEENABLE = 1'b1;

        #6
        WRITEREG = 3'd6;
        WRITEDATA = 8'd47;
        WRITEENABLE = 1'b1;
        READREG2 = 3'd6;
        
        #10
        WRITEDATA = 8'd97;
        WRITEENABLE = 1'b1;
        READREG2 = 3'd6;
        
        #10
        WRITEENABLE = 1'b0;
        
        #6
        WRITEREG = 3'd5;
        WRITEDATA = 8'd57;
        WRITEENABLE = 1'b1;
        
        #5
        WRITEENABLE = 1'b0;
        
        #2
        WRITEREG = 3'd3;
        WRITEDATA = 8'd45;
        WRITEENABLE = 1'b1;
        READREG2 = 3'd3;	
	
	#10
        $finish;
    end
    
    // clock signal generation
    always
        #5 CLK = ~CLK;
        

endmodule

Lab05-part2/second-marking/temp3/16070/Part2.v
/*
E/16/070
DE SILVA N.S.C.K.S.
LAB05 PART2
*/

//`include "regfile_tb.v"

// register file module
module reg_file(IN, OUT1, OUT2, INADDRESS, OUT1ADDRESS, OUT2ADDRESS, WRITE, CLK, RESET );

// port declaration
input [2:0] OUT1ADDRESS, OUT2ADDRESS, INADDRESS ; // for input and output register addresses
input WRITE, CLK, RESET ; // for control signals 
input [7:0] IN ; // for input data
output [7:0] OUT1, OUT2 ; // for output the data

// create a register array for implement eight, 8bit registers
reg [7:0] reg_arr [0:7] ; 

// read from regitser file is not synchronous with the clock signal
// read values with delay of 2 time units
assign #2 OUT1 = reg_arr[OUT1ADDRESS] ; 
assign #2 OUT2 = reg_arr[OUT2ADDRESS] ;

// write given data to the given register at rising edge of the clock 
// delay for write is 2 time units
always @ (posedge CLK)
begin
	if(WRITE==1 && RESET == 0) begin
		case (INADDRESS)
			3'b000 : begin
					#2 reg_arr [0] <= IN;
				 end
			3'b001 : begin
					#2 reg_arr [1] <= IN;
				 end	
			3'b010 : begin
					#2 reg_arr [2] <= IN;
				 end
			3'b011 : begin
					#2 reg_arr [3] <= IN;
				 end
			3'b100 : begin
					#2 reg_arr [4] <= IN;
				 end
			3'b101 : begin
					#2 reg_arr [5] <= IN;
				 end
			3'b110 : begin
					#2 reg_arr [6] <= IN;
				 end
			3'b111 : begin
					#2 reg_arr [7] <= IN;
				 end 
		endcase
	end
end

// the reset of the registers is not synchronous with the clock signal
integer i ;
always @ (RESET)
begin
	if(RESET) begin
		#2            // delay for rest is two time units
		for(i=0; i<8; i=i+1) begin
			reg_arr[i] <= 0 ; // make each value zero
		end
	end
end

endmodule

Lab05-part2/second-marking/temp3/16054/reg_file_tb_groundtruth.v
module reg_file_tb_groundtruth;
    
    reg [7:0] WRITEDATA;
    reg [2:0] WRITEREG, READREG1, READREG2;
    reg CLK, RESET, WRITEENABLE; 
    wire [7:0] REGOUT1, REGOUT2;
    
    reg_file myregfile(WRITEDATA, REGOUT1, REGOUT2, WRITEREG, READREG1, READREG2, WRITEENABLE, CLK, RESET);
       
    initial
    begin
        CLK = 1'b1;
        
        // generate files needed to plot the waveform using GTKWave
        $dumpfile("waveDump.vcd");
		$dumpvars(1, reg_file_tb_groundtruth);
        
        // assign values with time to input signals to see output 
        RESET = 1'b0;
        WRITEENABLE = 1'b0;
        
        #1
        RESET = 1'b1;
        READREG1 = 3'd0;
        READREG2 = 3'd4;
        
        #8
        RESET = 1'b0;
        
        #11
        READREG1 = 3'd2;
        WRITEREG = 3'd2;
        WRITEDATA = 8'd95;
        WRITEENABLE = 1'b1;
        
        #10
        WRITEENABLE = 1'b0;
        
        #1
        READREG1 = 3'd2;
        
        #9
        WRITEREG = 3'd1;
        WRITEDATA = 8'd28;
        WRITEENABLE = 1'b1;
        READREG1 = 3'd1;
        
        #10
        WRITEENABLE = 1'b0;
        
        #10
        WRITEREG = 3'd4;
        WRITEDATA = 8'd6;
        WRITEENABLE = 1'b1;
        
        #10
        WRITEDATA = 8'd15;
        WRITEENABLE = 1'b1;
        
        #10
        WRITEENABLE = 1'b0;
        
        #6
        WRITEREG = 3'd1;
        WRITEDATA = 8'd50;
        WRITEENABLE = 1'b1;
        
        #5
        WRITEENABLE = 1'b0;
        
        #10
        $finish;
    end
    
    // clock signal generation
    always
        #5 CLK = ~CLK;
        

endmodule

Lab05-part2/second-marking/temp3/16173/waveDump.vcd
$date
	Sun May 10 14:07:43 2020
$end
$version
	Icarus Verilog
$end
$timescale
	1s
$end
$scope module reg_file_tb_groundtruth $end
$var wire 8 ! REGOUT1 [7:0] $end
$var wire 8 " REGOUT2 [7:0] $end
$var reg 1 # CLK $end
$var reg 3 $ READREG1 [2:0] $end
$var reg 3 % READREG2 [2:0] $end
$var reg 1 & RESET $end
$var reg 8 ' WRITEDATA [7:0] $end
$var reg 1 ( WRITEENABLE $end
$var reg 3 ) WRITEREG [2:0] $end
$upscope $end
$enddefinitions $end
#0
$dumpvars
bx )
0(
bx '
0&
bx %
bx $
1#
bx "
bx !
$end
#1
b0 !
b100 %
b0 $
1&
#3
b0 "
#5
0#
#9
0&
#10
1#
#15
0#
#20
1#
1(
b1011111 '
b10 )
b10 $
#22
b1011111 !
#25
0#
#30
1#
0(
#35
0#
#40
b0 !
1#
b1 $
1(
b11100 '
b1 )
#42
b11100 !
#45
0#
#50
1#
0(
#55
0#
#60
1#
1(
b110 '
b100 )
#62
b110 "
#65
0#
#70
1#
b1111 '
#72
b1111 "
#75
0#
#80
1#
0(
#85
0#
#86
1(
b110010 '
b1 )
#90
1#
#91
0(
#92
b110010 !
