Lab05-part2/second-marking/temp3/16087/e16087_lab5_part2.v
//CO224 Computer Architecture
//Lab 5 - Building a Simple Processor
//Part 2 – Register File
//REG. NO: E/16/087

//////////////////////////////////////////////
/*
module reg_file_tb;
    
    reg [7:0] WRITEDATA;
    reg [2:0] WRITEREG, READREG1, READREG2;
    reg CLK, RESET, WRITEENABLE; 
    wire [7:0] REGOUT1, REGOUT2;
    
    reg_file myregfile(WRITEDATA, REGOUT1, REGOUT2, WRITEREG, READREG1, READREG2, WRITEENABLE, CLK, RESET);
       
    initial
    begin
        CLK = 1'b1;
        
        // generate files needed to plot the waveform using GTKWave
        $dumpfile("reg_file_wavedata.vcd");
		$dumpvars(0, reg_file_tb);
        
        // assign values with time to input signals to see output 
        RESET = 1'b0;
        WRITEENABLE = 1'b0;
        
        #1
        RESET = 1'b1;
        READREG1 = 3'd0;
        READREG2 = 3'd4;
        
        #8
        RESET = 1'b0;
        
        #5
        WRITEREG = 3'd2;
        WRITEDATA = 8'd95;
        WRITEENABLE = 1'b1;
        
        #10
        WRITEENABLE = 1'b0;
        
        #1
        READREG1 = 3'd2;
        
        #9
        WRITEREG = 3'd1;
        WRITEDATA = 8'd28;
        WRITEENABLE = 1'b1;
        READREG1 = 3'd1;
        
        #10
        WRITEENABLE = 1'b0;
        
        #10
        WRITEREG = 3'd4;
        WRITEDATA = 8'd6;
        WRITEENABLE = 1'b1;
        
        #10
        WRITEDATA = 8'd15;
        WRITEENABLE = 1'b1;
        
        #10
        WRITEENABLE = 1'b0;
        
        #6
        WRITEREG = 3'd1;
        WRITEDATA = 8'd50;
        WRITEENABLE = 1'b1;
        
        #5
        WRITEENABLE = 1'b0;
        
        #10
        $finish;
    end
    
    // clock signal generation
    always
        #5 CLK = ~CLK;
        

endmodule
*/
//////////////////////////////////////////////

module reg_file(IN, OUT1, OUT2, INADDRESS, OUT1ADDRESS, OUT2ADDRESS, WRITE, CLK, RESET);
  //Data input,
  input [7:0] IN; 
  //INADDRESS = register number to store that data in
  //OUT1ADDRESS and OUT2ADDRESS = register numbers where data should be retrieved from
  input [2:0] OUT1ADDRESS, OUT2ADDRESS, INADDRESS;
  //WRITE to accommodate the WRITEENABLE control signal
  //CLOCK and RESET signals for synchronization
  input WRITE, CLK, RESET;

  //OUT1 and OUT2 = dual data outputs
  output reg [7:0] OUT1, OUT2;

  //An array of 8 registers each of 8 bits
  reg [7:0] a_reg_file[7:0]; 
 
  //Reset
  always @ (*)
  begin
    if(RESET)
    begin
      #2
      a_reg_file[0] = 8'd0;
      a_reg_file[1] = 8'd0;
      a_reg_file[2] = 8'd0;
      a_reg_file[3] = 8'd0;
      a_reg_file[4] = 8'd0;
      a_reg_file[5] = 8'd0;
      a_reg_file[6] = 8'd0;
      a_reg_file[7] = 8'd0;
      end 
    end

  //OUT1ADDRESS and OUT2ADDRESS = the register numbers where data should be retrieved from.
  //registers identified by OUT1ADDRESS and OUT2ADDRESS, read asynchronously and the values load onto OUT1 and OUT2 respectively
  always @(*)
  begin
    if(~RESET)
    begin
      #2
      //Save data stored at OUT1ADDRESS into OUT1
      OUT1 <=  a_reg_file[OUT1ADDRESS];
      //Save data stored at OUT2ADDRESS into OUT2 
      OUT2 <=  a_reg_file[OUT2ADDRESS]; 
    end  
  end

  always @(posedge CLK)
  begin
    #2
    a_reg_file[INADDRESS] <= IN;
  end

endmodule

Lab05-part2/second-marking/temp3/16054/reg_file_tb_groundtruth.v
module reg_file_tb_groundtruth;
    
    reg [7:0] WRITEDATA;
    reg [2:0] WRITEREG, READREG1, READREG2;
    reg CLK, RESET, WRITEENABLE; 
    wire [7:0] REGOUT1, REGOUT2;
    
    reg_file myregfile(WRITEDATA, REGOUT1, REGOUT2, WRITEREG, READREG1, READREG2, WRITEENABLE, CLK, RESET);
       
    initial
    begin
        CLK = 1'b1;
        
        // generate files needed to plot the waveform using GTKWave
        $dumpfile("waveDump.vcd");
		$dumpvars(1, reg_file_tb_groundtruth);
        
        // assign values with time to input signals to see output 
        RESET = 1'b0;
        WRITEENABLE = 1'b0;
        
        #1
        RESET = 1'b1;
        READREG1 = 3'd0;
        READREG2 = 3'd4;
        
        #8
        RESET = 1'b0;
        
        #11
        READREG1 = 3'd2;
        WRITEREG = 3'd2;
        WRITEDATA = 8'd95;
        WRITEENABLE = 1'b1;
        
        #10
        WRITEENABLE = 1'b0;
        
        #1
        READREG1 = 3'd2;
        
        #9
        WRITEREG = 3'd1;
        WRITEDATA = 8'd28;
        WRITEENABLE = 1'b1;
        READREG1 = 3'd1;
        
        #10
        WRITEENABLE = 1'b0;
        
        #10
        WRITEREG = 3'd4;
        WRITEDATA = 8'd6;
        WRITEENABLE = 1'b1;
        
        #10
        WRITEDATA = 8'd15;
        WRITEENABLE = 1'b1;
        
        #10
        WRITEENABLE = 1'b0;
        
        #6
        WRITEREG = 3'd1;
        WRITEDATA = 8'd50;
        WRITEENABLE = 1'b1;
        
        #5
        WRITEENABLE = 1'b0;
        
        #10
        $finish;
    end
    
    // clock signal generation
    always
        #5 CLK = ~CLK;
        

endmodule

Lab05-part2/second-marking/temp3/16087/waveDump.vcd
$date
	Fri May  8 19:05:27 2020
$end
$version
	Icarus Verilog
$end
$timescale
	1s
$end
$scope module reg_file_tb_groundtruth $end
$var wire 8 ! REGOUT1 [7:0] $end
$var wire 8 " REGOUT2 [7:0] $end
$var reg 1 # CLK $end
$var reg 3 $ READREG1 [2:0] $end
$var reg 3 % READREG2 [2:0] $end
$var reg 1 & RESET $end
$var reg 8 ' WRITEDATA [7:0] $end
$var reg 1 ( WRITEENABLE $end
$var reg 3 ) WRITEREG [2:0] $end
$upscope $end
$enddefinitions $end
#0
$dumpvars
bx )
0(
bx '
0&
bx %
bx $
1#
bx "
bx !
$end
#1
b100 %
b0 $
1&
#5
0#
#9
0&
#10
1#
#11
b0 "
b0 !
#15
0#
#20
1#
1(
b1011111 '
b10 )
b10 $
#24
b1011111 !
#25
0#
#30
1#
0(
#35
0#
#40
1#
b1 $
1(
b11100 '
b1 )
#42
b0 !
#44
b11100 !
#45
0#
#50
1#
0(
#55
0#
#60
1#
1(
b110 '
b100 )
#64
b110 "
#65
0#
#70
1#
b1111 '
#74
b1111 "
#75
0#
#80
1#
0(
#85
0#
#86
1(
b110010 '
b1 )
#90
1#
#91
0(
#94
b110010 !
