Lab05-part2/second-marking/temp3/16089/reg_file.v
module testbench;
    
    reg [7:0] IN;
    reg [2:0] INADDRESS, OUT1ADDRESS, OUT2ADDRESS;
    reg CLK, RESET, WRITEENABLE; 
    wire [7:0] REGOUT1, REGOUT2;

    reg [7:0] REGISTER[7:0];
    
    reg_file myregfile(IN, REGOUT1, REGOUT2, INADDRESS, OUT1ADDRESS, OUT2ADDRESS, WRITEENABLE, CLK, RESET);
       
    initial   //Initial Block 
    begin

        CLK = 1'b1;
        
    	//Generate the files needed to display the waveform using GTKWave
        $dumpfile("reg_file_wavedata.vcd");
		$dumpvars(0, testbench);
        
  		// Assign values to generate the GTK wave 
        RESET = 1'b0;
        WRITEENABLE = 1'b0;
        
        #1
        RESET = 1'b1;
        OUT1ADDRESS = 3'b000;
        OUT2ADDRESS = 3'b101;
        
        #8
        RESET = 1'b0;
        OUT2ADDRESS = 3'b111;
        
        
        #5
        INADDRESS = 3'b010;
        IN = 8'b01010111;
        WRITEENABLE = 1'b1;
        
        #10
        WRITEENABLE = 1'b0;
        
        #1
        OUT1ADDRESS = 3'b110;
        
        #9
        INADDRESS = 3'b001;
        IN = 8'b00011101;
        WRITEENABLE = 1'b1;
        OUT1ADDRESS = 3'b001;
        OUT2ADDRESS = 3'b110;
        
        #10
        WRITEENABLE = 1'b0;
        
        #10
        INADDRESS = 3'b100;
        IN = 8'b01000110;
        WRITEENABLE = 1'b1;
        
        #10
        IN = 8'b00001110;
        WRITEENABLE = 1'b1;
        OUT2ADDRESS = 3'b100;
        
        #10
        WRITEENABLE = 1'b0;
        
        #6
        INADDRESS = 3'b011;
        IN = 8'b10110010;
        WRITEENABLE = 1'b1;
        
        #5
        WRITEENABLE = 1'b0;

        #10
        INADDRESS = 3'b101;
        IN = 8'b01000110;
        WRITEENABLE = 1'b0;
        OUT2ADDRESS = 3'b101;

        #10
        INADDRESS = 3'b111;
        IN = 8'b00011101;
        WRITEENABLE = 1'b1;
        OUT1ADDRESS = 3'b001;

        #10
        $finish;
    end
    
    // clock signal generation

    always
        #5 CLK = ~CLK;
        

endmodule





module reg_file(IN, OUT1, OUT2, INADDRESS, OUT1ADDRESS, OUT2ADDRESS, WRITE, CLK, RESET); // Module of the register 

	input [2:0] INADDRESS, OUT1ADDRESS, OUT2ADDRESS; // Input values - Address values of IN, OUT1 and OUT2
	input [7:0] IN;  			// Input 8bit Value 
	input WRITE, CLK, RESET; 	//Inputs
	output [7:0] OUT1, OUT2;  	// Output 8 bit Values

	reg [7:0] REGISTER[7:0]; // 8 8bit Registers to Store 8bit values 
	reg OUT1, OUT2;			 // Define Output as registers 
	integer i; 				 // i Values of the loop

	always @ (posedge CLK) // Always block for the CLK
	begin

		if(WRITE)begin // When WRITE is enable, 

		#2
		REGISTER[INADDRESS] = IN; // Write the value in IN to the relevent register(register in the INADDRESS)

		#2
		OUT1 = REGISTER[OUT1ADDRESS]; //Read the value of the given register(address in OUT1ADDRESS) and load to the OUT1
		OUT2 = REGISTER[OUT2ADDRESS]; //Read the value of the given register(address in OUT3ADDRESS) and load to the OUT2

		end
	end


	always @ (posedge RESET) begin // Always block for the RESET 

		#2
		for(i=0; i<8; i = i +1) begin  // Positive edge of the RESET all the register values should be Zero(00000000)
			REGISTER[i] = 8'b00000000;	
		end

		#2
		OUT1 = REGISTER[OUT1ADDRESS]; //After the reset Values should be loades to the OUT1 and OUT2
		OUT2 = REGISTER[OUT2ADDRESS];

	end


	always @ (OUT1ADDRESS) begin //Always block for the OUT1ADDRESS

		if (!RESET) begin // When the RESET == 0, 
			#2
			OUT1 = REGISTER[OUT1ADDRESS]; // Values in the given register address(OUT1ADDRESS) should be loaded in to the OUT1
		end
	end


	always @ (OUT2ADDRESS) begin //Always block for the OUT2ADDRESS

		if (!RESET) begin    // When the RESET == 0, 
			#2
			OUT2 = REGISTER[OUT2ADDRESS];   // Values in the given register address(OUT2ADDRESS) should be loaded in to the OUT2
		end
	end

endmodule

Lab05-part2/second-marking/temp3/16054/reg_file_tb_groundtruth.v
module reg_file_tb_groundtruth;
    
    reg [7:0] WRITEDATA;
    reg [2:0] WRITEREG, READREG1, READREG2;
    reg CLK, RESET, WRITEENABLE; 
    wire [7:0] REGOUT1, REGOUT2;
    
    reg_file myregfile(WRITEDATA, REGOUT1, REGOUT2, WRITEREG, READREG1, READREG2, WRITEENABLE, CLK, RESET);
       
    initial
    begin
        CLK = 1'b1;
        
        // generate files needed to plot the waveform using GTKWave
        $dumpfile("waveDump.vcd");
		$dumpvars(1, reg_file_tb_groundtruth);
        
        // assign values with time to input signals to see output 
        RESET = 1'b0;
        WRITEENABLE = 1'b0;
        
        #1
        RESET = 1'b1;
        READREG1 = 3'd0;
        READREG2 = 3'd4;
        
        #8
        RESET = 1'b0;
        
        #11
        READREG1 = 3'd2;
        WRITEREG = 3'd2;
        WRITEDATA = 8'd95;
        WRITEENABLE = 1'b1;
        
        #10
        WRITEENABLE = 1'b0;
        
        #1
        READREG1 = 3'd2;
        
        #9
        WRITEREG = 3'd1;
        WRITEDATA = 8'd28;
        WRITEENABLE = 1'b1;
        READREG1 = 3'd1;
        
        #10
        WRITEENABLE = 1'b0;
        
        #10
        WRITEREG = 3'd4;
        WRITEDATA = 8'd6;
        WRITEENABLE = 1'b1;
        
        #10
        WRITEDATA = 8'd15;
        WRITEENABLE = 1'b1;
        
        #10
        WRITEENABLE = 1'b0;
        
        #6
        WRITEREG = 3'd1;
        WRITEDATA = 8'd50;
        WRITEENABLE = 1'b1;
        
        #5
        WRITEENABLE = 1'b0;
        
        #10
        $finish;
    end
    
    // clock signal generation
    always
        #5 CLK = ~CLK;
        

endmodule

Lab05-part2/second-marking/temp3/16076/waveDump.vcd
$date
	Fri May  8 18:44:37 2020
$end
$version
	Icarus Verilog
$end
$timescale
	1s
$end
$scope module reg_file_tb_groundtruth $end
$var wire 8 ! REGOUT1 [7:0] $end
$var wire 8 " REGOUT2 [7:0] $end
$var reg 1 # CLK $end
$var reg 3 $ READREG1 [2:0] $end
$var reg 3 % READREG2 [2:0] $end
$var reg 1 & RESET $end
$var reg 8 ' WRITEDATA [7:0] $end
$var reg 1 ( WRITEENABLE $end
$var reg 3 ) WRITEREG [2:0] $end
$upscope $end
$enddefinitions $end
#0
$dumpvars
bx )
0(
bx '
0&
bx %
bx $
1#
bx "
bx !
$end
#1
b100 %
b0 $
1&
#5
b0 "
b0 !
0#
#9
0&
#10
1#
#15
0#
#20
1#
1(
b1011111 '
b10 )
b10 $
#24
b1011111 !
#25
0#
#30
1#
0(
#35
0#
#40
1#
b1 $
1(
b11100 '
b1 )
#42
b0 !
#44
b11100 !
#45
0#
#50
1#
0(
#55
0#
#60
1#
1(
b110 '
b100 )
#64
b110 "
#65
0#
#70
1#
b1111 '
#74
b1111 "
#75
0#
#80
1#
0(
#85
0#
#86
1(
b110010 '
b1 )
#90
1#
#91
0(
#94
b110010 !
