Lab05-part2/temp3/16394/reg_file.v
/*
    Reg.No :E/16/394
    CO224 Lab 5 Reg_File.v
*/

module reg_file(IN ,OUT1 ,OUT2 ,INADDRESS ,OUTADDRESS1 ,OUTADDRESS2 ,WRITE ,CLK ,RESET);
    //register file with 8x8 bits registers
    //define inputs
    //input 8 bits data
    input [7:0] IN;
    // 3 bits input and output register addresses
    input [2:0] INADDRESS ,OUTADDRESS1 ,OUTADDRESS2 ;
    //1 bit inputs
    input WRITE ,CLK ,RESET ;
    //define    8 BITS outputs
    output [7:0] OUT1 ,OUT2 ;

    //8 bits 8 registers 
    reg [7:0] r_Block [0:7];
    //instantiate 8 bit register for out1 and out2
    reg [7:0] OUT1 ,OUT2;
    //define integer for reset all registers using for loop
    integer i ;
    //asynchronusly put registers to out 
 
    always @ (*)
    begin
        //choose Out1 according to outaddress1
        //add #2 delay to read 
        case (OUTADDRESS1)
        0 : OUT1 <= #2 r_Block[0] ;
        1 : OUT1 <= #2 r_Block[1] ;
        2 : OUT1 <= #2 r_Block[2] ;
        3 : OUT1 <= #2 r_Block[3] ;
        4 : OUT1 <= #2 r_Block[4] ;
        5 : OUT1 <= #2 r_Block[5] ;
        6 : OUT1 <= #2 r_Block[6] ;
        7 : OUT1 <= #2 r_Block[7] ;
        endcase
    end

   
    always @(*)
    begin
        //choose Out2 according to outaddress2
        //add #2 delay to read 
        case (OUTADDRESS2)
        0 : OUT2 <= #2 r_Block[0] ;
        1 : OUT2 <= #2 r_Block[1] ;
        2 : OUT2 <= #2 r_Block[2] ;
        3 : OUT2 <= #2 r_Block[3] ;
        4 : OUT2 <= #2 r_Block[4] ;
        5 : OUT2 <= #2 r_Block[5] ;
        6 : OUT2 <= #2 r_Block[6] ;
        7 : OUT2 <= #2 r_Block[7] ;
        endcase  
            
    end
    //synchronize with positve edge of clk 
    always @ (posedge CLK)
    begin
        //write data in IN to INADDRESS if write enabled
        if (WRITE == 1)
        begin
            //add #2 delay to write
            case (INADDRESS)
                0 : r_Block[0] = #2 IN;
                1 : r_Block[1] = #2 IN;
                2 : r_Block[2] = #2 IN;
                3 : r_Block[3] = #2 IN;
                4 : r_Block[4] = #2 IN;
                5 : r_Block[5] = #2 IN;
                6 : r_Block[6] = #2 IN;
                7 : r_Block[7] = #2 IN;
            endcase
            
        end
    end
    //asynchronizely reset all registers to 0
    always @ (RESET)
    begin
        //check reset == 1 add #2 delay
        if (RESET == 1)
        begin
            #2
            for (i =0 ;i <8 ;i = i+1)
            begin
                r_Block[i] <= 0;
            end
        end
    end
endmodule

Lab05-part2/second-marking/temp3/16054/reg_file_tb_groundtruth.v
module reg_file_tb_groundtruth;
    
    reg [7:0] WRITEDATA;
    reg [2:0] WRITEREG, READREG1, READREG2;
    reg CLK, RESET, WRITEENABLE; 
    wire [7:0] REGOUT1, REGOUT2;
    
    reg_file myregfile(WRITEDATA, REGOUT1, REGOUT2, WRITEREG, READREG1, READREG2, WRITEENABLE, CLK, RESET);
       
    initial
    begin
        CLK = 1'b1;
        
        // generate files needed to plot the waveform using GTKWave
        $dumpfile("waveDump.vcd");
		$dumpvars(1, reg_file_tb_groundtruth);
        
        // assign values with time to input signals to see output 
        RESET = 1'b0;
        WRITEENABLE = 1'b0;
        
        #1
        RESET = 1'b1;
        READREG1 = 3'd0;
        READREG2 = 3'd4;
        
        #8
        RESET = 1'b0;
        
        #11
        READREG1 = 3'd2;
        WRITEREG = 3'd2;
        WRITEDATA = 8'd95;
        WRITEENABLE = 1'b1;
        
        #10
        WRITEENABLE = 1'b0;
        
        #1
        READREG1 = 3'd2;
        
        #9
        WRITEREG = 3'd1;
        WRITEDATA = 8'd28;
        WRITEENABLE = 1'b1;
        READREG1 = 3'd1;
        
        #10
        WRITEENABLE = 1'b0;
        
        #10
        WRITEREG = 3'd4;
        WRITEDATA = 8'd6;
        WRITEENABLE = 1'b1;
        
        #10
        WRITEDATA = 8'd15;
        WRITEENABLE = 1'b1;
        
        #10
        WRITEENABLE = 1'b0;
        
        #6
        WRITEREG = 3'd1;
        WRITEDATA = 8'd50;
        WRITEENABLE = 1'b1;
        
        #5
        WRITEENABLE = 1'b0;
        
        #10
        $finish;
    end
    
    // clock signal generation
    always
        #5 CLK = ~CLK;
        

endmodule

Lab05-part2/groundtruth/waveDump.vcd
$date
	Fri May  8 02:50:44 2020
$end
$version
	Icarus Verilog
$end
$timescale
	1s
$end
$scope module reg_file_tb_groundtruth $end
$var wire 8 ! REGOUT1 [7:0] $end
$var wire 8 " REGOUT2 [7:0] $end
$var reg 1 # CLK $end
$var reg 3 $ READREG1 [2:0] $end
$var reg 3 % READREG2 [2:0] $end
$var reg 1 & RESET $end
$var reg 8 ' WRITEDATA [7:0] $end
$var reg 1 ( WRITEENABLE $end
$var reg 3 ) WRITEREG [2:0] $end
$upscope $end
$enddefinitions $end
#0
$dumpvars
bx )
0(
bx '
0&
bx %
bx $
1#
bx "
bx !
$end
#1
b100 %
b0 $
1&
#5
b0 "
b0 !
0#
#9
0&
#10
1#
#15
0#
#20
1#
1(
b1011111 '
b10 )
b10 $
#24
b1011111 !
#25
0#
#30
1#
0(
#35
0#
#40
1#
b1 $
1(
b11100 '
b1 )
#42
b0 !
#44
b11100 !
#45
0#
#50
1#
0(
#55
0#
#60
1#
1(
b110 '
b100 )
#64
b110 "
#65
0#
#70
1#
b1111 '
#74
b1111 "
#75
0#
#80
1#
0(
#85
0#
#86
1(
b110010 '
b1 )
#90
1#
#91
0(
#94
b110010 !
