Lab05-part2/second-marking/temp3/16061/reg_file.v
/*	register file module
	Author - Chandula JPDM
	Date - 02/05/2020
*/

module reg_file(IN, OUT1, OUT2, INADDRESS, OUT1ADDRESS, OUT2ADDRESS, WRITE, CLK, RESET);

//define input and output ports
input [2:0] OUT1ADDRESS, OUT2ADDRESS, INADDRESS;
input [7:0] IN;
input CLK, RESET, WRITE;
output [7:0] OUT1, OUT2;

reg [7:0] OUT1, OUT2;
integer i;

integer t = 0; //calculate total delay time
integer resetDelay = 2;
integer readDelay = 2;

//Registers
reg [7:0] register [7:0];

//-------------- (if reset == 1 values of all the registers become 0) ----------------------
//level triggered reset
always @(*) begin
	
	if(RESET == 1) begin
		
		//assing 0 for each register
		for( i = 0; i<8; i = i+1) begin
			register[i] = 8'b00000000;
		end
		
	end
	
end
//---------------------------------------------------------------------------------------------------------------



/* 
	*Read the value from a given register address
	*This block will only initiate when out1address or out2address or  register values changes only.
*/
always @(OUT1ADDRESS or OUT2ADDRESS or  register[INADDRESS]) begin
		
		//if reset == 1 when registers are reading time delay should be equal to addition of  reset delay and read delay
		if(RESET==1) begin
			
			t = resetDelay+ readDelay;
	
		end
		
		else begin 
			
			t=readDelay;
		
		end

		#t
		
		//setting values for out1
		case (OUT2ADDRESS)
			
		3'b000 : OUT2 = register[0];
		3'b001 : OUT2 = register[1];
		3'b010 : OUT2 = register[2];
		3'b011 : OUT2 = register[3];
		3'b100 : OUT2 = register[4];
		3'b101 : OUT2 = register[5];
		3'b110 : OUT2 = register[6];
		3'b111 : OUT2 = register[7];	
		
		endcase

		//setting value for out2	
		case (OUT1ADDRESS)
			
		3'b000 : OUT1 = register[0];
		3'b001 : OUT1 = register[1];
		3'b010 : OUT1 = register[2];
		3'b011 : OUT1 = register[3];
		3'b100 : OUT1 = register[4];
		3'b101 : OUT1 = register[5];
		3'b110 : OUT1 = register[6];
		3'b111 : OUT1 = register[7];	
		
		endcase

end


/*
	*Write a value to a given register address
	*This block only initiate when positive edge of  the clock
*/
always @(posedge CLK) begin

	if(WRITE==1)
		
		#2 //delay for write a value to a register

		//write data to register for given input address
		case (INADDRESS)
	
			3'b000 : register[0] = IN;
			3'b001 : register[1] = IN;
			3'b010 : register[2] = IN;
			3'b011 : register[3] = IN;
			3'b100 : register[4] = IN;
			3'b101 : register[5] = IN;
			3'b110 : register[6] = IN;
			3'b111 : register[7] = IN;	
	
		endcase
	
end

endmodule

Lab05-part2/second-marking/temp3/16054/reg_file_tb_groundtruth.v
module reg_file_tb_groundtruth;
    
    reg [7:0] WRITEDATA;
    reg [2:0] WRITEREG, READREG1, READREG2;
    reg CLK, RESET, WRITEENABLE; 
    wire [7:0] REGOUT1, REGOUT2;
    
    reg_file myregfile(WRITEDATA, REGOUT1, REGOUT2, WRITEREG, READREG1, READREG2, WRITEENABLE, CLK, RESET);
       
    initial
    begin
        CLK = 1'b1;
        
        // generate files needed to plot the waveform using GTKWave
        $dumpfile("waveDump.vcd");
		$dumpvars(1, reg_file_tb_groundtruth);
        
        // assign values with time to input signals to see output 
        RESET = 1'b0;
        WRITEENABLE = 1'b0;
        
        #1
        RESET = 1'b1;
        READREG1 = 3'd0;
        READREG2 = 3'd4;
        
        #8
        RESET = 1'b0;
        
        #11
        READREG1 = 3'd2;
        WRITEREG = 3'd2;
        WRITEDATA = 8'd95;
        WRITEENABLE = 1'b1;
        
        #10
        WRITEENABLE = 1'b0;
        
        #1
        READREG1 = 3'd2;
        
        #9
        WRITEREG = 3'd1;
        WRITEDATA = 8'd28;
        WRITEENABLE = 1'b1;
        READREG1 = 3'd1;
        
        #10
        WRITEENABLE = 1'b0;
        
        #10
        WRITEREG = 3'd4;
        WRITEDATA = 8'd6;
        WRITEENABLE = 1'b1;
        
        #10
        WRITEDATA = 8'd15;
        WRITEENABLE = 1'b1;
        
        #10
        WRITEENABLE = 1'b0;
        
        #6
        WRITEREG = 3'd1;
        WRITEDATA = 8'd50;
        WRITEENABLE = 1'b1;
        
        #5
        WRITEENABLE = 1'b0;
        
        #10
        $finish;
    end
    
    // clock signal generation
    always
        #5 CLK = ~CLK;
        

endmodule

Lab05-part2/second-marking/temp3/16061/waveDump.vcd
$date
	Fri May  8 18:57:41 2020
$end
$version
	Icarus Verilog
$end
$timescale
	1s
$end
$scope module reg_file_tb_groundtruth $end
$var wire 8 ! REGOUT1 [7:0] $end
$var wire 8 " REGOUT2 [7:0] $end
$var reg 1 # CLK $end
$var reg 3 $ READREG1 [2:0] $end
$var reg 3 % READREG2 [2:0] $end
$var reg 1 & RESET $end
$var reg 8 ' WRITEDATA [7:0] $end
$var reg 1 ( WRITEENABLE $end
$var reg 3 ) WRITEREG [2:0] $end
$upscope $end
$enddefinitions $end
#0
$dumpvars
bx )
0(
bx '
0&
bx %
bx $
1#
bx "
bx !
$end
#1
b100 %
b0 $
1&
#5
b0 !
b0 "
0#
#9
0&
#10
1#
#15
0#
#20
1#
1(
b1011111 '
b10 )
b10 $
#24
b1011111 !
#25
0#
#30
1#
0(
#35
0#
#40
1#
b1 $
1(
b11100 '
b1 )
#42
b0 !
#44
b11100 !
#45
0#
#50
1#
0(
#55
0#
#60
1#
1(
b110 '
b100 )
#64
b110 "
#65
0#
#70
1#
b1111 '
#74
b1111 "
#75
0#
#80
1#
0(
#85
0#
#86
1(
b110010 '
b1 )
#90
1#
#91
0(
#94
b110010 !
