Lab05-part2/second-marking/temp3/16232/reg_file.v
/*************************
   E16232
   F.S.Marzook
   Lab5_Part2
   Register File Module 
**************************/

`timescale 1ns / 1ns

module reg_file (IN, OUT1, OUT2, INADDRESS, OUT1ADDRESS, OUT2ADDRESS, WRITE, CLK, RESET);
	
	//declare inputs
	input [7:0] IN;
	input [2:0] INADDRESS, OUT1ADDRESS, OUT2ADDRESS;
	input WRITE, CLK, RESET;
	//declare output
	output [7:0] OUT1, OUT2;

	integer i;

	reg [7:0] myreg[7:0];			//array of registers
	reg [7:0] temp1,temp2;			//temperary registers
	
	parameter DELAY = 2;


	//whenever the reset changes and it becomes high, all the registers must be zero
	always @(RESET)
	begin
		if(RESET==1)
		begin
			#DELAY
			for(i=0;i<8;i=i+1)
			begin
				myreg[i] = 0;		//all the registers are cleared
			end	
		end
	end
	

	//the output should change always when the output address change.
	//It doesn't depend in the clk edge
	always @(*)
	begin
		temp1 =  myreg[OUT1ADDRESS];
		temp2 =  myreg[OUT2ADDRESS];		
	end

	assign  #DELAY OUT1 = temp1;			//assign output values in the register
	assign  #DELAY OUT2 = temp2;
	

	//input should change in every positive edge and reset
	always @(posedge CLK,RESET)
	begin
		//when reset is low and the write signal is high the input value should change
		if(RESET == 0 && WRITE == 1)
		begin
				#DELAY 
				myreg[INADDRESS] = IN;	// write the value in input to the register
		end
	end

endmodule

Lab05-part2/second-marking/temp3/16054/reg_file_tb_groundtruth.v
module reg_file_tb_groundtruth;
    
    reg [7:0] WRITEDATA;
    reg [2:0] WRITEREG, READREG1, READREG2;
    reg CLK, RESET, WRITEENABLE; 
    wire [7:0] REGOUT1, REGOUT2;
    
    reg_file myregfile(WRITEDATA, REGOUT1, REGOUT2, WRITEREG, READREG1, READREG2, WRITEENABLE, CLK, RESET);
       
    initial
    begin
        CLK = 1'b1;
        
        // generate files needed to plot the waveform using GTKWave
        $dumpfile("waveDump.vcd");
		$dumpvars(1, reg_file_tb_groundtruth);
        
        // assign values with time to input signals to see output 
        RESET = 1'b0;
        WRITEENABLE = 1'b0;
        
        #1
        RESET = 1'b1;
        READREG1 = 3'd0;
        READREG2 = 3'd4;
        
        #8
        RESET = 1'b0;
        
        #11
        READREG1 = 3'd2;
        WRITEREG = 3'd2;
        WRITEDATA = 8'd95;
        WRITEENABLE = 1'b1;
        
        #10
        WRITEENABLE = 1'b0;
        
        #1
        READREG1 = 3'd2;
        
        #9
        WRITEREG = 3'd1;
        WRITEDATA = 8'd28;
        WRITEENABLE = 1'b1;
        READREG1 = 3'd1;
        
        #10
        WRITEENABLE = 1'b0;
        
        #10
        WRITEREG = 3'd4;
        WRITEDATA = 8'd6;
        WRITEENABLE = 1'b1;
        
        #10
        WRITEDATA = 8'd15;
        WRITEENABLE = 1'b1;
        
        #10
        WRITEENABLE = 1'b0;
        
        #6
        WRITEREG = 3'd1;
        WRITEDATA = 8'd50;
        WRITEENABLE = 1'b1;
        
        #5
        WRITEENABLE = 1'b0;
        
        #10
        $finish;
    end
    
    // clock signal generation
    always
        #5 CLK = ~CLK;
        

endmodule

Lab05-part2/second-marking/temp3/16049/waveDump.vcd
$date
	Fri May  8 19:05:26 2020
$end
$version
	Icarus Verilog
$end
$timescale
	1s
$end
$scope module reg_file_tb_groundtruth $end
$var wire 8 ! REGOUT1 [7:0] $end
$var wire 8 " REGOUT2 [7:0] $end
$var reg 1 # CLK $end
$var reg 3 $ READREG1 [2:0] $end
$var reg 3 % READREG2 [2:0] $end
$var reg 1 & RESET $end
$var reg 8 ' WRITEDATA [7:0] $end
$var reg 1 ( WRITEENABLE $end
$var reg 3 ) WRITEREG [2:0] $end
$upscope $end
$enddefinitions $end
#0
$dumpvars
bx )
0(
bx '
0&
bx %
bx $
1#
bx "
bx !
$end
#1
b100 %
b0 $
1&
#5
b0 "
b0 !
0#
#9
0&
#10
1#
#15
0#
#20
1#
1(
b1011111 '
b10 )
b10 $
#24
b1011111 !
#25
0#
#30
1#
0(
#35
0#
#40
1#
b1 $
1(
b11100 '
b1 )
#42
b0 !
#44
b11100 !
#45
0#
#50
1#
0(
#55
0#
#60
1#
1(
b110 '
b100 )
#64
b110 "
#65
0#
#70
1#
b1111 '
#74
b1111 "
#75
0#
#80
1#
0(
#85
0#
#86
1(
b110010 '
b1 )
#90
1#
#91
0(
#94
b110010 !
